MANIFEST.in
setup.cfg
setup.py
tw/__init__.py
tw.tinymce.egg-info/PKG-INFO
tw.tinymce.egg-info/SOURCES.txt
tw.tinymce.egg-info/dependency_links.txt
tw.tinymce.egg-info/entry_points.txt
tw.tinymce.egg-info/namespace_packages.txt
tw.tinymce.egg-info/not-zip-safe
tw.tinymce.egg-info/requires.txt
tw.tinymce.egg-info/top_level.txt
tw/tinymce/__init__.py
tw/tinymce/descriptions.py
tw/tinymce/release.py
tw/tinymce/widgets.py
tw/tinymce/static/javascript/blank.htm
tw/tinymce/static/javascript/license.txt
tw/tinymce/static/javascript/tiny_mce.js
tw/tinymce/static/javascript/tiny_mce_popup.js
tw/tinymce/static/javascript/tiny_mce_src.js
tw/tinymce/static/javascript/langs/ar.js
tw/tinymce/static/javascript/langs/ca.js
tw/tinymce/static/javascript/langs/cs.js
tw/tinymce/static/javascript/langs/cy.js
tw/tinymce/static/javascript/langs/da.js
tw/tinymce/static/javascript/langs/de.js
tw/tinymce/static/javascript/langs/el.js
tw/tinymce/static/javascript/langs/en.js
tw/tinymce/static/javascript/langs/es.js
tw/tinymce/static/javascript/langs/fa.js
tw/tinymce/static/javascript/langs/fa_ca.js
tw/tinymce/static/javascript/langs/fi.js
tw/tinymce/static/javascript/langs/fr.js
tw/tinymce/static/javascript/langs/fr_ca.js
tw/tinymce/static/javascript/langs/he.js
tw/tinymce/static/javascript/langs/hu.js
tw/tinymce/static/javascript/langs/is.js
tw/tinymce/static/javascript/langs/it.js
tw/tinymce/static/javascript/langs/ja-euc-jp.js
tw/tinymce/static/javascript/langs/ja.js
tw/tinymce/static/javascript/langs/ja_euc-jp.js
tw/tinymce/static/javascript/langs/ja_shift-jis.js
tw/tinymce/static/javascript/langs/ja_shift_jis.js
tw/tinymce/static/javascript/langs/ja_utf-8.js
tw/tinymce/static/javascript/langs/ko.js
tw/tinymce/static/javascript/langs/nb.js
tw/tinymce/static/javascript/langs/nl.js
tw/tinymce/static/javascript/langs/nn.js
tw/tinymce/static/javascript/langs/pl.js
tw/tinymce/static/javascript/langs/pt.js
tw/tinymce/static/javascript/langs/pt_br.js
tw/tinymce/static/javascript/langs/readme.txt
tw/tinymce/static/javascript/langs/ro.js
tw/tinymce/static/javascript/langs/ru.js
tw/tinymce/static/javascript/langs/ru_CP1251.js
tw/tinymce/static/javascript/langs/ru_KOI8-R.js
tw/tinymce/static/javascript/langs/si.js
tw/tinymce/static/javascript/langs/sk.js
