Metadata-Version: 1.0
Name: tw.tinymce
Version: 0.8
Summary: TinyMCE WYSIWYG rich text editor for ToscaWidgets
Home-page: http://toscawidgets.org
Author: Alberto Valverde Gonzalez
Author-email: alberto@toscat.net
License: UNKNOWN
Download-URL: http://toscawidgets.org/download
Keywords: toscawidgets.widgets
Platform: UNKNOWN
